<?xml version="1.0" encoding="UTF-8"?>
<!DOCTYPE mapper PUBLIC "-//mybatis.org//DTD Mapper 3.0//EN" "http://mybatis.org/dtd/mybatis-3-mapper.dtd">
<mapper namespace="com.sinjinsong.icourse.core.dao.order.OrderDOMapper">
    <resultMap id="BaseResultMap" type="com.sinjinsong.icourse.core.domain.entity.order.OrderDO">
        <id column="id" property="id"></id>
        <result column="place_time" property="placeTime"></result>
        <result column="price" property="price"></result>
        <result column="status" property="status" javaType="com.sinjinsong.icourse.core.enumeration.order.OrderStatus"></result>
        <result column="discount" property="discount"></result>
        <result column="pay_type" property="payType" javaType="com.sinjinsong.icourse.core.enumeration.order.PayType"></result>
        <association column="student_id" property="student" select="com.sinjinsong.icourse.core.dao.student.StudentDOMapper.selectByPrimaryKey"></association>
        <association column="class_id" property="classDO" select="com.sinjinsong.icourse.core.dao.course.ClassDOMapper.selectByPrimaryKey"></association>
    </resultMap>
    <sql id="Base_Column_List">
        <!--
          WARNING - @mbggenerated
          This element is automatically generated by MyBatis Generator, do not modify.
        -->
        id, student_id, class_id, place_time, price, status, discount, pay_type
    </sql>
    <select id="selectByPrimaryKey" parameterType="java.lang.Long" resultMap="BaseResultMap">
        <!--
          WARNING - @mbggenerated
          This element is automatically generated by MyBatis Generator, do not modify.
        -->
        select
        <include refid="Base_Column_List"/>
        from `order`
        where id = #{id,jdbcType=BIGINT}
    </select>
    <delete id="deleteByPrimaryKey" parameterType="java.lang.Long">
        <!--
          WARNING - @mbggenerated
          This element is automatically generated by MyBatis Generator, do not modify.
        -->
        delete from `order`
        where id = #{id,jdbcType=BIGINT}
    </delete>
    <insert id="insert" parameterType="com.sinjinsong.icourse.core.domain.entity.order.OrderDO">
        <!--
          WARNING - @mbggenerated
          This element is automatically generated by MyBatis Generator, do not modify.
        -->
        insert into `order` (id, student_id, class_id,
        place_time, price, status,
        discount, pay_type)
        values (#{id,jdbcType=BIGINT}, #{studentId,jdbcType=BIGINT}, #{classId,jdbcType=BIGINT},
        #{placeTime,jdbcType=TIMESTAMP}, #{price,jdbcType=DOUBLE}, #{status,jdbcType=SMALLINT},
        #{discount,jdbcType=DOUBLE}, #{payType,jdbcType=SMALLINT})
    </insert>

    <update id="updateByPrimaryKeySelective" parameterType="com.sinjinsong.icourse.core.domain.entity.order.OrderDO">
        <!--
          WARNING - @mbggenerated
          This element is automatically generated by MyBatis Generator, do not modify.
        -->
        update `order`
        <set>
            <if test="studentId != null">
                student_id = #{studentId,jdbcType=BIGINT},
            </if>
            <if test="classId != null">
                class_id = #{classId,jdbcType=BIGINT},
            </if>
            <if test="placeTime != null">
                place_time = #{placeTime,jdbcType=TIMESTAMP},
            </if>
            <if test="price != null">
                price = #{price,jdbcType=DOUBLE},
            </if>
            <if test="status != null">
                status = #{status,jdbcType=SMALLINT},
            </if>
            <if test="discount != null">
                discount = #{discount,jdbcType=DOUBLE},
            </if>
            <if test="payType != null">
                pay_type = #{payType,jdbcType=SMALLINT},
            </if>
        </set>
        where id = #{id,jdbcType=BIGINT}
    </update>

    <select id="findAll" resultMap="BaseResultMap">
        select
        <include refid="Base_Column_List"/>
        from `order`
        order by place_time desc
    </select>


    <select id="findByCondition" resultMap="BaseResultMap">
        select
        <include refid="Base_Column_List"/>
        from `order`
        <where>
            <if test="condition.userId != null">
                `order`.user = #{condition.userId}
            </if>
            <if test="condition.begin != null and condition.end != null">
                and `order`.place_time between #{condition.begin} and #{condition.end}
            </if>
            <if test="condition.status != null">
                and `order`.status = #{condition.status}
            </if>
        </where>
        order by place_time desc
    </select>
    <select id="findByInstitutionSettlementId" resultMap="BaseResultMap">
        select
        <include refid="Base_Column_List"/>
        from `order`
        where id in
        (
        select order_id from institution_settlement_order
        where institution_settlement_id = #{institution_settlement_id}
        )
    </select>
</mapper>